{
  "project_info": {
    "project_number": "557457440311",
    "project_id": "acma-intl",
    "storage_bucket": "acma-intl.appspot.com"
  },
  "client": [
    {
      "client_info": {
        "mobilesdk_app_id": "1:557457440311:android:b13ef15c14185c102989b2",
        "android_client_info": {
          "package_name": "com.saqib.acma_intl"
        }
      },
      "oauth_client": [
        {
          "client_id": "557457440311-4l049jjhtd34t0f5ud7ticdsks6ej9tn.apps.googleusercontent.com",
          "client_type": 1,
          "android_info": {
            "package_name": "com.saqib.acma_intl",
            "certificate_hash": "9bbfde373b2ee55da3a981f52b6624f23aee8fd4"
          }
        },
        {
          "client_id": "557457440311-96opgn97u707e2grd1lsum6s9astfbea.apps.googleusercontent.com",
          "client_type": 3
        }
      ],
      "api_key": [
        {
          "current_key": "AIzaSyDTzGtNYc9rqQIcYsj6gV2eofMFHIRGnp4"
        }
      ],
      "services": {
        "appinvite_service": {
          "other_platform_oauth_client": [
            {
              "client_id": "557457440311-96opgn97u707e2grd1lsum6s9astfbea.apps.googleusercontent.com",
              "client_type": 3
            },
            {
              "client_id": "557457440311-foiqmgsjf1plrlehvqqm67dnteh4pkhn.apps.googleusercontent.com",
              "client_type": 2,
              "ios_info": {
                "bundle_id": "com.saqib.acmaIntl"
              }
            }
          ]
        }
      }
    }
  ],
  "configuration_version": "1"
}